simple_di/__init__.py
simple_di/providers.py
simple_di/py.typed
simple_di-0.1.5.dist-info/LICENSE
simple_di-0.1.5.dist-info/METADATA
simple_di-0.1.5.dist-info/WHEEL
simple_di-0.1.5.dist-info/top_level.txt
simple_di-0.1.5.dist-info/RECORD
