Metadata-Version: 2.1
Name: simple-di
Version: 0.1.5
Summary: simple dependency injection library
Home-page: https://github.com/bentoml/simple_di
Author: bojiang
Author-email: bojiang_@outlook.com
License: Apache License 2.0
Platform: UNKNOWN
Classifier: Operating System :: OS Independent
Classifier: Development Status :: 2 - Pre-Alpha
Classifier: Programming Language :: Python :: 3.6
Classifier: Programming Language :: Python :: 3.7
Classifier: Programming Language :: Python :: 3.8
Classifier: Programming Language :: Python :: 3.9
Classifier: Programming Language :: Python :: Implementation :: CPython
Requires-Python: >=3.6.1
Provides-Extra: test
License-File: LICENSE
